Metadata-Version: 1.0
Name: package-pertama
Version: 0.2
Summary: Latihan membuat package di Python
Home-page: http://github.com/yanwarsolah/package-pertama
Author: Yanwar Solahudin
Author-email: yanwarsolah@gmail.com
License: MIT
Platform: UNKNOWN
